termcursor/__init__.py
termcursor/constants.py
termcursor/errors.py
termcursor/structures.py
termcursor/termcursor.py
termcursor-1.0.0.dist-info/LICENSE
termcursor-1.0.0.dist-info/METADATA
termcursor-1.0.0.dist-info/WHEEL
termcursor-1.0.0.dist-info/top_level.txt
termcursor-1.0.0.dist-info/RECORD
