Metadata-Version: 2.1
Name: termcursor
Version: 1.0.0
Summary: Hiding or showing the console cursor on Windows and Unix platforms with the Python Standard Library only
Author: Richárd Ádám Vécsey Dr.
Maintainer: Richárd Ádám Vécsey Dr.
Project-URL: Homepage, https://github.com/richardvecsey/termcursor
Classifier: Development Status :: 3 - Alpha
Classifier: Environment :: Console
Classifier: Intended Audience :: Developers
Classifier: Intended Audience :: End Users/Desktop
Classifier: Intended Audience :: System Administrators
Classifier: License :: OSI Approved :: MIT License
Classifier: Operating System :: Microsoft :: Windows
Classifier: Operating System :: POSIX :: Linux 
Classifier: Operating System :: Unix
Classifier: Operating System :: OS Independent
Classifier: Programming Language :: Python :: 3
Classifier: Programming Language :: Python :: 3.10
Classifier: Topic :: Software Development
Classifier: Topic :: Software Development :: Libraries
Classifier: Topic :: Software Development :: Libraries :: Python Modules
Classifier: Topic :: Software Development :: User Interfaces
Classifier: Topic :: System :: Console Fonts
Classifier: Topic :: Terminals
Requires-Python: >=3.10
License-File: LICENSE
